gobotz_rabbitmq/__init__.py
gobotz_rabbitmq/consumer.py
gobotz_rabbitmq/message.py
gobotz_rabbitmq/reply.py
gobotz_rabbitmq/rmq.py
gobotz_rabbitmq-0.0.16.dist-info/LICENSE
gobotz_rabbitmq-0.0.16.dist-info/WHEEL
gobotz_rabbitmq-0.0.16.dist-info/METADATA
gobotz_rabbitmq-0.0.16.dist-info/RECORD
