Metadata-Version: 2.1
Name: gobotz-rabbitmq
Version: 0.0.16
Summary: aioamqp wrapper for rabbitmq
License: Unlicense
Author: GoBotz
Author-email: info@gobotz.io
Requires-Python: >=3.10,<4.0
Classifier: License :: Other/Proprietary License
Classifier: Programming Language :: Python :: 3
Classifier: Programming Language :: Python :: 3.10
Requires-Dist: aioamqp (>=0.15.0,<0.16.0)
Requires-Dist: ujson (>=5.3.0,<6.0.0)
